dtcc_core-0.9.3.dist-info/RECORD
dtcc_core-0.9.3.dist-info/WHEEL
dtcc_core-0.9.3.dist-info/METADATA
dtcc_core-0.9.3.dist-info/licenses/LICENSE
dtcc_core/CMakeLists.txt
dtcc_core/__init__.py
dtcc_core/proto/dtcc.proto
dtcc_core/io/city.py
dtcc_core/io/logging.py
dtcc_core/io/pointcloud_directory.py
dtcc_core/io/generic.py
dtcc_core/io/__init__.py
dtcc_core/io/footprints.py
dtcc_core/io/meshes.py
dtcc_core/io/landuse.py
dtcc_core/io/utils.py
dtcc_core/io/pointcloud.py
dtcc_core/io/roadnetwork.py
dtcc_core/io/raster.py
dtcc_core/io/info.py
dtcc_core/io/container/pointcloud_container.py
dtcc_core/io/container/__init__.py
dtcc_core/io/cityjson/write_cityjson.py
dtcc_core/io/cityjson/__init__.py
dtcc_core/io/cityjson/cityjson.py
dtcc_core/io/cityjson/utils.py
dtcc_core/io/scripts/dtcc_info.py
dtcc_core/io/scripts/__init__.py
dtcc_core/common/__init__.py
dtcc_core/common/dtcc_logging.py
dtcc_core/cpp/dtcc_builder.cpp
dtcc_core/cpp/include/Smoother.h
dtcc_core/cpp/include/Utils.h
dtcc_core/cpp/include/BoundaryConditions.h
dtcc_core/cpp/include/BoundingBoxTree.h
dtcc_core/cpp/include/Intersection.h
dtcc_core/cpp/include/BoundingBox.h
dtcc_core/cpp/include/Logging.h
dtcc_core/cpp/include/VertexSmoother.h
dtcc_core/cpp/include/BuildingProcessor.h
dtcc_core/cpp/include/Timer.h
dtcc_core/cpp/include/Constants.h
dtcc_core/cpp/include/PointCloudProcessor.h
dtcc_core/cpp/include/MeshBuilder.h
dtcc_core/cpp/include/StiffnessMatrix.h
dtcc_core/cpp/include/Table.h
dtcc_core/cpp/include/Hashing.h
dtcc_core/cpp/include/Triangulate.h
dtcc_core/cpp/include/MeshQualityMetrics.h
dtcc_core/cpp/include/Polyfix.h
dtcc_core/cpp/include/MeshProcessor.h
dtcc_core/cpp/include/VolumeMeshBuilder.h
dtcc_core/cpp/include/Geometry.h
dtcc_core/cpp/include/KDTreeVectorOfVectorsAdaptor.h
dtcc_core/cpp/include/fem/SparseMatrix.h
dtcc_core/cpp/include/fem/Elasticity.h
dtcc_core/cpp/include/fem/Assembler.h
dtcc_core/cpp/include/fem/Poisson.h
dtcc_core/cpp/include/fem/BilinearForm.h
dtcc_core/cpp/include/fem/LinearSolver.h
dtcc_core/cpp/include/fem/forms/docker-create-container
